lories/__init__.py
lories/__main__.py
lories/_version.py
lories/location.py
lories/settings.py
lories/system.py
lories/util.py
lories/_core/__init__.py
lories/_core/_activator.py
lories/_core/_channel.py
lories/_core/_channels.py
lories/_core/_component.py
lories/_core/_configurations.py
lories/_core/_configurator.py
lories/_core/_connector.py
lories/_core/_constant.py
lories/_core/_context.py
lories/_core/_converter.py
lories/_core/_data.py
lories/_core/_database.py
lories/_core/_entity.py
lories/_core/_listener.py
lories/_core/_registrator.py
lories/_core/_resource.py
lories/_core/_resources.py
lories/_core/typing.py
lories/application/__init__.py
lories/application/interface.py
lories/application/main.py
lories/application/view/__init__.py
lories/application/view/interface.py
lories/application/view/assets/__init__.py
lories/application/view/assets/accordion.css
lories/application/view/assets/application.css
lories/application/view/assets/favicon.ico
lories/application/view/assets/logo.png
lories/application/view/assets/weather.css
lories/application/view/login/__init__.py
lories/application/view/login/authentication.py
lories/application/view/login/page.py
lories/application/view/login/user.py
lories/application/view/pages/__init__.py
lories/application/view/pages/footer.py
lories/application/view/pages/group.py
lories/application/view/pages/header.py
lories/application/view/pages/page.py
lories/application/view/pages/registry.py
lories/application/view/pages/view.py
lories/application/view/pages/components/__init__.py
lories/application/view/pages/components/group.py
lories/application/view/pages/components/page.py
lories/application/view/pages/components/system.py
lories/application/view/pages/components/weather.py
lories/application/view/pages/layout/__init__.py
lories/application/view/pages/layout/card.py
lories/application/view/pages/layout/page.py
lories/components/__init__.py
lories/components/access.py
lories/components/camera.py
lories-0.15.4.dist-info/licenses/LICENSE
lories-0.15.4.dist-info/METADATA
lories-0.15.4.dist-info/WHEEL
lories-0.15.4.dist-info/entry_points.txt
lories-0.15.4.dist-info/top_level.txt
lories-0.15.4.dist-info/RECORD
