Metadata-Version: 2.4
Name: lories
Version: 0.15.4
Summary: This project provides a set of core functions and framework for Local Resource Integration and Execution Systems by ISC Konstanz e.V.
Author: ISC Konstanz e.V.
Maintainer-email: Adrian Minde <adrian.minde@isc-konstanz.de>
License-Expression: LGPL-3.0-or-later
Project-URL: author, https://isc-konstanz.de
Project-URL: source, https://github.com/isc-konstanz/lories/
Project-URL: issues, https://github.com/isc-konstanz/lories/issues
Classifier: Programming Language :: Python :: 3
Classifier: Programming Language :: Python :: 3 :: Only
Classifier: Programming Language :: Python :: 3.9
Classifier: Programming Language :: Python :: 3.10
Classifier: Programming Language :: Python :: 3.11
Classifier: Programming Language :: Python :: 3.12
Classifier: Programming Language :: Python :: 3.13
Classifier: Operating System :: OS Independent
Requires-Python: >=3.9
License-File: LICENSE
Requires-Dist: tomli>=1.1; python_version < "3.11"
Requires-Dist: numpy>=1.21
Requires-Dist: pandas>=1.3
Requires-Dist: tzlocal>=5.1
Requires-Dist: requests>=2.31
Provides-Extra: postgresql
Requires-Dist: sqlalchemy>=2.0; extra == "postgresql"
Requires-Dist: psycopg2>=2.9; extra == "postgresql"
Provides-Extra: mariadb
Requires-Dist: sqlalchemy>=2.0; extra == "mariadb"
Requires-Dist: pymysql>=1.1; extra == "mariadb"
Provides-Extra: mysql
Requires-Dist: sqlalchemy>=2.0; extra == "mysql"
Requires-Dist: pymysql>=1.1; extra == "mysql"
Provides-Extra: influx
Requires-Dist: influxdb-client; extra == "influx"
Provides-Extra: serial
Requires-Dist: pyserial; extra == "serial"
Provides-Extra: modbus
Requires-Dist: pymodbus<=3.9; extra == "modbus"
Provides-Extra: revpi
Requires-Dist: revpimodio2; extra == "revpi"
Provides-Extra: dash
Requires-Dist: dash; extra == "dash"
Requires-Dist: dash-auth; extra == "dash"
Requires-Dist: dash-bootstrap-component; extra == "dash"
Requires-Dist: flask-bcrypt; extra == "dash"
Requires-Dist: flask-login; extra == "dash"
Provides-Extra: sim
Requires-Dist: openpyxl; extra == "sim"
Requires-Dist: matplotlib; extra == "sim"
Requires-Dist: seaborn; extra == "sim"
Requires-Dist: tqdm; extra == "sim"
Provides-Extra: doc
Requires-Dist: graphviz; extra == "doc"
Requires-Dist: sphinx; extra == "doc"
Requires-Dist: sphinx-autoapi; extra == "doc"
Requires-Dist: pydata-sphinx-theme; extra == "doc"
Requires-Dist: myst-parser; extra == "doc"
Provides-Extra: dev
Requires-Dist: pre-commit; extra == "dev"
Requires-Dist: ruff; extra == "dev"
Dynamic: license-file
